ShiyanlouGitJiaochengHeji20160904/README.md
ShiyanlouGitJiaochengHeji20160904/__init__.py
ShiyanlouGitJiaochengHeji20160904/__main__.py
ShiyanlouGitJiaochengHeji20160904/file.epub
ShiyanlouGitJiaochengHeji20160904/index.html
ShiyanlouGitJiaochengHeji20160904/css/__init__.py
ShiyanlouGitJiaochengHeji20160904/css/annotations.css
ShiyanlouGitJiaochengHeji20160904/css/main.css
ShiyanlouGitJiaochengHeji20160904/css/normalize.css
ShiyanlouGitJiaochengHeji20160904/css/popup.css
ShiyanlouGitJiaochengHeji20160904/font/__init__.py
ShiyanlouGitJiaochengHeji20160904/font/fontello.eot
ShiyanlouGitJiaochengHeji20160904/font/fontello.svg
ShiyanlouGitJiaochengHeji20160904/font/fontello.ttf
ShiyanlouGitJiaochengHeji20160904/font/fontello.woff
ShiyanlouGitJiaochengHeji20160904/img/__init__.py
ShiyanlouGitJiaochengHeji20160904/img/annotator-glyph-sprite.png
ShiyanlouGitJiaochengHeji20160904/img/annotator-icon-sprite.png
ShiyanlouGitJiaochengHeji20160904/img/apple-touch-icon.png
ShiyanlouGitJiaochengHeji20160904/img/cancelfullscreen.png
ShiyanlouGitJiaochengHeji20160904/img/close.png
ShiyanlouGitJiaochengHeji20160904/img/fullscreen.png
ShiyanlouGitJiaochengHeji20160904/img/loader.gif
ShiyanlouGitJiaochengHeji20160904/img/menu-icon.png
ShiyanlouGitJiaochengHeji20160904/img/save.png
ShiyanlouGitJiaochengHeji20160904/img/saved.png
ShiyanlouGitJiaochengHeji20160904/img/settings-s.png
ShiyanlouGitJiaochengHeji20160904/img/settings.png
ShiyanlouGitJiaochengHeji20160904/img/star.png
ShiyanlouGitJiaochengHeji20160904/js/__init__.py
ShiyanlouGitJiaochengHeji20160904/js/epub.js
ShiyanlouGitJiaochengHeji20160904/js/epub.min.js
ShiyanlouGitJiaochengHeji20160904/js/epub.min.map
ShiyanlouGitJiaochengHeji20160904/js/hooks.min.js
ShiyanlouGitJiaochengHeji20160904/js/hooks.min.map
ShiyanlouGitJiaochengHeji20160904/js/reader.js
ShiyanlouGitJiaochengHeji20160904/js/reader.js.map
ShiyanlouGitJiaochengHeji20160904/js/reader.min.js
ShiyanlouGitJiaochengHeji20160904/js/reader.min.map
shiyanlou_git_jiaocheng_heji_20160904-2024.3.1.0.dist-info/METADATA
shiyanlou_git_jiaocheng_heji_20160904-2024.3.1.0.dist-info/WHEEL
shiyanlou_git_jiaocheng_heji_20160904-2024.3.1.0.dist-info/entry_points.txt
shiyanlou_git_jiaocheng_heji_20160904-2024.3.1.0.dist-info/top_level.txt
shiyanlou_git_jiaocheng_heji_20160904-2024.3.1.0.dist-info/RECORD
